README.rst
setup.py
smh/__init__.py
smh/atmospheres.py
smh/core.py
smh/isochrones.py
smh/moog.py
smh/nlte.py
smh/profiles.py
smh/session.py
smh/specutils.py
smh/utils.py
smh.egg-info/PKG-INFO
smh.egg-info/SOURCES.txt
smh.egg-info/dependency_links.txt
smh.egg-info/requires.txt
smh.egg-info/top_level.txt
smh/gui/__init__.py
smh/gui/chemicalabundances.py
smh/gui/database.py
smh/gui/doppler.py
smh/gui/equivalentwidths.py
smh/gui/gui_core.py
smh/gui/main.py
smh/gui/nlte.py
smh/gui/normalisation.py
smh/gui/plotting.py
smh/gui/qualitycontrol.py
smh/gui/stellarparameters.py
smh/gui/summary.py
smh/gui/synthesis.py
smh/gui/tabs.py
smh/gui/uncertainties.py