Metadata-Version: 1.0
Name: smh
Version: 0.1
Summary: Spectroscopy Made Hard
Home-page: http://www.github.com/andycasey/smh/
Author: Andrew R. Casey
Author-email: andy@astrowizici.st
License: GPLv2
Platform: UNKNOWN
